drf_swagger_extras/__init__.py
drf_swagger_extras/decorators.py
drf_swagger_extras/hacks.py
drf_swagger_extras/routers.py
drf_swagger_extras/schemas.py
drf_swagger_extras-0.1.0.dev1.dist-info/DESCRIPTION.rst
drf_swagger_extras-0.1.0.dev1.dist-info/METADATA
drf_swagger_extras-0.1.0.dev1.dist-info/RECORD
drf_swagger_extras-0.1.0.dev1.dist-info/WHEEL
drf_swagger_extras-0.1.0.dev1.dist-info/metadata.json
drf_swagger_extras-0.1.0.dev1.dist-info/top_level.txt
