Metadata-Version: 2.0
Name: drf-swagger-extras
Version: 0.1.0.dev1
Summary: Django REST Framework extras for better Swagger/OpenAPI self-documentation
Home-page: https://github.com/ssaavedra/drf-swagger-extras
Author: Santiago Saavedra
Author-email: ssaavedra@gpul.org
License: MIT
Platform: UNKNOWN
Classifier: Development Status :: 3 - Alpha
Classifier: Environment :: Web Environment
Classifier: Framework :: Django
Classifier: Intended Audience :: Developers
Classifier: License :: OSI Approved :: MIT License
Classifier: Operating System :: OS Independent
Classifier: Programming Language :: Python :: 2
Classifier: Programming Language :: Python :: 3
Classifier: Topic :: Internet :: WWW/HTTP
Classifier: Topic :: Software Development :: Documentation
Requires-Dist: coreapi (~=2.0)
Requires-Dist: djangorestframework (~=3.4)
Requires-Dist: openapi-codec (~=1.0)
Requires-Dist: six (~=1.10)
Provides-Extra: dev
Requires-Dist: pypandoc (~=1.2); extra == 'dev'
Provides-Extra: test
Requires-Dist: coverage (~=4.2); extra == 'test'
Requires-Dist: pytest (~=3.0.2); extra == 'test'
Requires-Dist: tox (~=2.3); extra == 'test'
